Metadata-Version: 2.4
Name: python-ydotool
Version: 1.1.0
Summary: ydotool client implemented in Python
Home-page: https://github.com/Antares0982/pydotool
Download-URL: https://github.com/Antares0982/pydotool/releases
Author: Antares0982
Author-email: antares@alyr.dev
Project-URL: Bug Tracker, https://github.com/Antares0982/pydotool/issues
Project-URL: Source Code, https://github.com/Antares0982/pydotool
Platform: linux
Classifier: Development Status :: 5 - Production/Stable
Classifier: Operating System :: POSIX :: Linux
Classifier: Programming Language :: Python :: 3.9
Classifier: Programming Language :: Python :: 3.10
Classifier: Programming Language :: Python :: 3.11
Classifier: Programming Language :: Python :: 3.12
Classifier: Programming Language :: Python :: 3.13
Classifier: Programming Language :: Python :: 3.14
Classifier: Programming Language :: Python :: 3.15
Requires-Python: >=3.9
License-File: LICENSE
Dynamic: description
Dynamic: description-content-type
Dynamic: download-url
Dynamic: home-page
Dynamic: license-file
Dynamic: project-url
Dynamic: summary
